fluidtopics/connector/__init__.py
fluidtopics/connector/client.py
fluidtopics/connector/helpers/__init__.py
fluidtopics/connector/helpers/attachment_update_checker.py
fluidtopics/connector/helpers/fake_client.py
fluidtopics/connector/helpers/metadata_inheritor.py
fluidtopics/connector/helpers/metadata_update_checker.py
fluidtopics/connector/helpers/publication_checker.py
fluidtopics/connector/internal/__init__.py
fluidtopics/connector/internal/constants.py
fluidtopics/connector/internal/id_provider.py
fluidtopics/connector/internal/reporter.py
fluidtopics/connector/internal/sender.py
fluidtopics/connector/internal/utils.py
fluidtopics/connector/internal/zip_builder.py
fluidtopics/connector/internal/fson/__init__.py
fluidtopics/connector/internal/fson/fson_attachments.py
fluidtopics/connector/internal/fson/fson_body.py
fluidtopics/connector/internal/fson/fson_metadata.py
fluidtopics/connector/internal/fson/fson_publication.py
fluidtopics/connector/internal/fson/fson_resource.py
fluidtopics/connector/internal/fson/fson_right.py
fluidtopics/connector/internal/fson/fson_section.py
fluidtopics/connector/internal/fson/fson_version.py
fluidtopics/connector/model/__init__.py
fluidtopics/connector/model/attachment.py
fluidtopics/connector/model/attachment_update.py
fluidtopics/connector/model/body.py
fluidtopics/connector/model/document.py
fluidtopics/connector/model/external_document.py
fluidtopics/connector/model/has_metadata.py
fluidtopics/connector/model/metadata.py
fluidtopics/connector/model/metadata_update.py
fluidtopics/connector/model/publication.py
fluidtopics/connector/model/resource.py
fluidtopics/connector/model/right.py
fluidtopics/connector/model/right_update.py
fluidtopics/connector/model/structured_document.py
fluidtopics/connector/model/topic.py
fluidtopics/connector/model/unstructured_document.py
fluidtopics-1.0.3.data/data/COPYING.LESSER
fluidtopics-1.0.3.dist-info/COPYING.LESSER
fluidtopics-1.0.3.dist-info/METADATA
fluidtopics-1.0.3.dist-info/WHEEL
fluidtopics-1.0.3.dist-info/top_level.txt
fluidtopics-1.0.3.dist-info/zip-safe
fluidtopics-1.0.3.dist-info/RECORD
