Metadata-Version: 2.1
Name: fluidtopics
Version: 1.0.3
Summary: Fluid Topics API
Home-page: UNKNOWN
Author: Antidot
Author-email: opensource@antidot.net
License: UNKNOWN
Platform: UNKNOWN
Classifier: Development Status :: 5 - Production/Stable
Classifier: Operating System :: OS Independent
Classifier: Intended Audience :: Developers
Classifier: Programming Language :: Python :: 3
Classifier: License :: OSI Approved :: GNU Lesser General Public License v2 or later (LGPLv2+)
Requires-Python: >=3.5
Requires-Dist: assertpy
Requires-Dist: autovalue
Requires-Dist: pyckson
Requires-Dist: injector
Requires-Dist: requests
